fabric/__init__.py
fabric/adapters/__init__.py
fabric/adapters/base.py
fabric/adapters/fastapi.py
fabric/adapters/flask.py
fabric/api/__init__.py
fabric/api/router.py
fabric/api/schemas.py
fabric/core/__init__.py
fabric/core/collector.py
fabric/core/config.py
fabric/core/events.py
fabric/core/fabric.py
fabric/core/models.py
fabric/dashboard/dist/index.html
fabric/dashboard/dist/assets/Dashboard-Cpx1BHb3.js
fabric/dashboard/dist/assets/Endpoints-LTZfEiMv.js
fabric/dashboard/dist/assets/Requests-CSiI4Rqn.js
fabric/dashboard/dist/assets/Settings-OsOyN5Nk.js
fabric/dashboard/dist/assets/dayjs.min-CxMP4GVf.js
fabric/dashboard/dist/assets/echarts-BywJijcg.js
fabric/dashboard/dist/assets/index-5ZQV0oeG.css
fabric/dashboard/dist/assets/index-BYCcWbA5.js
fabric/dashboard/dist/assets/index-CkWQk8ob.js
fabric/dashboard/dist/assets/vue-vendor-w28tHAkY.js
fabric/storage/__init__.py
fabric/storage/base.py
fabric/storage/memory.py
fabric/utils/__init__.py
fabric/utils/serializer.py
fabric/utils/time.py
fabric_monitor-0.1.0.dist-info/licenses/LICENSE
fabric_monitor-0.1.0.dist-info/METADATA
fabric_monitor-0.1.0.dist-info/WHEEL
fabric_monitor-0.1.0.dist-info/top_level.txt
fabric_monitor-0.1.0.dist-info/RECORD
